localdata_mcp/__init__.py
localdata_mcp/localdata_mcp.py
localdata_mcp/py.typed
localdata_mcp-1.3.0.dist-info/licenses/LICENSE
localdata_mcp-1.3.0.dist-info/METADATA
localdata_mcp-1.3.0.dist-info/WHEEL
localdata_mcp-1.3.0.dist-info/entry_points.txt
localdata_mcp-1.3.0.dist-info/top_level.txt
localdata_mcp-1.3.0.dist-info/RECORD
