Metadata-Version: 2.4
Name: localdata-mcp
Version: 1.3.0
Summary: A dynamic MCP server for local databases and text files.
Author-email: "Christian C. Berclaz" <christian.berclaz@mac.com>
License-Expression: MIT
Project-URL: Homepage, https://github.com/chrisgve/localdata-mcp
Project-URL: Repository, https://github.com/chrisgve/localdata-mcp
Project-URL: Documentation, https://github.com/chrisgve/localdata-mcp#readme
Project-URL: Bug Tracker, https://github.com/chrisgve/localdata-mcp/issues
Keywords: mcp,model-context-protocol,database,ai,assistant
Classifier: Development Status :: 4 - Beta
Classifier: Intended Audience :: Developers
Classifier: Programming Language :: Python :: 3
Classifier: Programming Language :: Python :: 3.10
Classifier: Programming Language :: Python :: 3.11
Classifier: Programming Language :: Python :: 3.12
Classifier: Topic :: Database
Classifier: Topic :: Software Development :: Libraries :: Python Modules
Requires-Python: >=3.10
License-File: LICENSE
Requires-Dist: fastmcp
Requires-Dist: pandas>=1.3.0
Requires-Dist: sqlalchemy>=1.4.0
Requires-Dist: psycopg2-binary
Requires-Dist: mysql-connector-python
Requires-Dist: pyyaml>=5.4.0
Requires-Dist: toml>=0.10.0
Requires-Dist: psutil>=5.8.0
Requires-Dist: openpyxl>=3.0.0
Requires-Dist: defusedxml>=0.7.0
Requires-Dist: xlrd>=2.0.0
Requires-Dist: odfpy>=1.4.0
Requires-Dist: pyarrow>=10.0.0
Requires-Dist: lxml>=4.6.0
Requires-Dist: numbers-parser>=4.0.0
Requires-Dist: h5py>=3.0.0
Provides-Extra: dev
Requires-Dist: pytest>=6.0.0; extra == "dev"
Requires-Dist: pytest-cov; extra == "dev"
Requires-Dist: black; extra == "dev"
Requires-Dist: isort; extra == "dev"
Requires-Dist: flake8; extra == "dev"
Requires-Dist: mypy; extra == "dev"
Requires-Dist: numbers-parser>=4.15.0; extra == "dev"
Requires-Dist: pandas-stubs; extra == "dev"
Requires-Dist: types-toml; extra == "dev"
Requires-Dist: types-PyYAML; extra == "dev"
Provides-Extra: modern-databases
Requires-Dist: redis>=6.0.0; extra == "modern-databases"
Requires-Dist: elasticsearch>=9.0.0; extra == "modern-databases"
Requires-Dist: pymongo>=4.0.0; extra == "modern-databases"
Requires-Dist: influxdb-client>=1.40.0; extra == "modern-databases"
Requires-Dist: neo4j>=5.0.0; extra == "modern-databases"
Requires-Dist: couchdb>=1.2.0; extra == "modern-databases"
Dynamic: license-file
